hashtable/__init__.py
hashtable/hashtable.py
hashtable_python-1.0.3.dist-info/LICENSE
hashtable_python-1.0.3.dist-info/METADATA
hashtable_python-1.0.3.dist-info/WHEEL
hashtable_python-1.0.3.dist-info/top_level.txt
hashtable_python-1.0.3.dist-info/RECORD
