Metadata-Version: 2.1
Name: hashtable-python
Version: 1.0.3
Summary: HashTable implementation in python
Home-page: https://github.com/gvrosun/hashtable
Author: Rosun GV
Author-email: gvrosun@gmail.com
License: UNKNOWN
Project-URL: Bug Tracker, https://github.com/gvrosun/hashtable/issues
Keywords: HashTable,Data Stuctures,development
Platform: UNKNOWN
Classifier: Development Status :: 5 - Production/Stable
Classifier: Programming Language :: Python :: 3
Classifier: Programming Language :: Python :: 3.6
Classifier: Programming Language :: Python :: 3.7
Classifier: Programming Language :: Python :: 3.8
Classifier: Programming Language :: Python :: 3.9
Classifier: Programming Language :: Python :: 3 :: Only
Classifier: License :: OSI Approved :: MIT License
Classifier: Operating System :: OS Independent
Requires-Python: >=3.6, <4
